api_flow/__init__.py
api_flow/__main__.py
api_flow/complex_namespace.py
api_flow/config.py
api_flow/context.py
api_flow/flow.py
api_flow/functions.py
api_flow/profiles.py
api_flow/request.py
api_flow/step.py
api_flow/template.py
api_flow-0.5.2.dist-info/LICENSE
api_flow-0.5.2.dist-info/METADATA
api_flow-0.5.2.dist-info/WHEEL
api_flow-0.5.2.dist-info/top_level.txt
api_flow-0.5.2.dist-info/RECORD
