Metadata-Version: 2.1
Name: api-flow
Version: 0.5.2
Summary: A utility for running flows of chained API calls
Home-page: https://github.com/rothomas/api_flow.git
Author: Rob Thomas
Author-email: pypi@sharedsecret.com
License: UNKNOWN
Project-URL: Bug Tracker, https://github.com/rothomas/api_flow/issues
Platform: UNKNOWN
Classifier: Development Status :: 3 - Alpha
Classifier: Programming Language :: Python :: 3
Classifier: License :: OSI Approved :: MIT License
Classifier: Operating System :: OS Independent
Requires-Python: >=3.6
License-File: LICENSE
